pkglogger/__init__.py
pkglogger/pkglogger.py
pkglogger-0.0.16.0.dist-info/LICENSE.txt
pkglogger-0.0.16.0.dist-info/METADATA
pkglogger-0.0.16.0.dist-info/WHEEL
pkglogger-0.0.16.0.dist-info/top_level.txt
pkglogger-0.0.16.0.dist-info/RECORD
