Metadata-Version: 2.1
Name: pkglogger
Version: 0.0.16.0
Summary: This package help you to keep logs
Home-page: https://github.com/pypa/sampleproject
Author: Avik Das
Author-email: avik_das_2017@cba.isb.edu
License: UNKNOWN
Project-URL: Bug Tracker, https://github.com/pypa/sampleproject/issues
Platform: UNKNOWN
Classifier: Programming Language :: Python :: 2
Classifier: License :: OSI Approved :: MIT License
Classifier: Operating System :: OS Independent
Requires-Python: >=2.0
License-File: LICENSE.txt
